beancount_blue/__init__.py
beancount_blue/amortize.py
beancount_blue/calc_uk_gains.py
beancount_blue/tag.py
beancount_blue-1.0.1.dist-info/licenses/LICENSE
beancount_blue-1.0.1.dist-info/METADATA
beancount_blue-1.0.1.dist-info/WHEEL
beancount_blue-1.0.1.dist-info/top_level.txt
beancount_blue-1.0.1.dist-info/RECORD
