Metadata-Version: 2.4
Name: beancount_blue
Version: 1.0.1
Summary: This is a template repository for Python projects that use uv for their dependency management.
Author-email: Mark Scannell <mescanne@gmail.com>
Project-URL: Homepage, https://mescanne.github.io/beancount-blue/
Project-URL: Repository, https://github.com/mescanne/beancount-blue
Project-URL: Documentation, https://mescanne.github.io/beancount-blue/
Keywords: python
Classifier: Intended Audience :: Developers
Classifier: Programming Language :: Python
Classifier: Programming Language :: Python :: 3
Classifier: Programming Language :: Python :: 3.9
Classifier: Programming Language :: Python :: 3.10
Classifier: Programming Language :: Python :: 3.11
Classifier: Programming Language :: Python :: 3.12
Classifier: Programming Language :: Python :: 3.13
Classifier: Topic :: Software Development :: Libraries :: Python Modules
Requires-Python: <4.0,>=3.9
License-File: LICENSE
Requires-Dist: beancount
Requires-Dist: python-dateutil
Dynamic: license-file
